{
	"_meta":	{
		"version":	12,
		"format":	"v12_old",
		"level":	10,
		"sublevel":	5,
		"checksum":	0
	},
	"path":	"P:\\CROC\\EDITOR\\MAPS\\GAME\\ISLAND1\\LEVEL1\\MAP6.MAP",
	"name":	"Default Blank Map",
	"width":	16,
	"height":	16,
	"depth":	32,
	"style":	"wood",
	"flags":	0,
	"cd_track":	0,
	"background":	29,
	"effect":	"none",
	"wait":	0,
	"ambience":	"bird",
	"start_rotation":	-0.041748046875,
	"tracks":	[{
			"position":	[0, 0, 0],
			"yr":	0,
			"index":	56
		}, {
			"position":	[4, 0, 0],
			"yr":	0.25,
			"index":	56
		}, {
			"position":	[0, 0, 1],
			"yr":	0.75,
			"index":	8
		}, {
			"position":	[4, 0, 1],
			"yr":	0.25,
			"index":	8
		}, {
			"position":	[0, 0, 2],
			"yr":	0.75,
			"index":	8
		}, {
			"position":	[4, 0, 2],
			"yr":	0.25,
			"index":	8
		}, {
			"position":	[1, 0, 3],
			"yr":	0,
			"index":	34
		}, {
			"position":	[3, 0, 3],
			"yr":	0.25,
			"index":	34
		}, {
			"position":	[2, 0, 4],
			"yr":	0,
			"index":	8
		}, {
			"position":	[1, 0, 5],
			"yr":	0.5,
			"index":	8
		}, {
			"position":	[2, 0, 5],
			"yr":	0.5,
			"index":	8
		}, {
			"position":	[3, 0, 5],
			"yr":	0.5,
			"index":	8
		}, {
			"position":	[0, 0, 6],
			"yr":	0.75,
			"index":	8
		}, {
			"position":	[4, 0, 6],
			"yr":	0.25,
			"index":	8
		}, {
			"position":	[1, 0, 7],
			"yr":	0,
			"index":	34
		}, {
			"position":	[3, 0, 7],
			"yr":	0.25,
			"index":	34
		}, {
			"position":	[2, 0, 8],
			"yr":	0,
			"index":	8
		}, {
			"position":	[0, 8, 0],
			"yr":	0,
			"index":	34
		}, {
			"position":	[2, 8, 0],
			"yr":	0,
			"index":	79
		}, {
			"position":	[4, 8, 0],
			"yr":	0.25,
			"index":	34
		}, {
			"position":	[1, 8, 1],
			"yr":	0,
			"index":	2
		}, {
			"position":	[2, 8, 1],
			"yr":	0,
			"index":	40
		}, {
			"position":	[3, 8, 1],
			"yr":	0,
			"index":	2
		}, {
			"position":	[1, 8, 2],
			"yr":	0.25,
			"index":	40
		}, {
			"position":	[2, 8, 2],
			"yr":	0.5,
			"index":	38
		}, {
			"position":	[3, 8, 2],
			"yr":	0.75,
			"index":	40
		}, {
			"position":	[2, 8, 3],
			"yr":	0.75,
			"index":	128
		}, {
			"position":	[1, 8, 6],
			"yr":	0.5,
			"index":	131
		}, {
			"position":	[2, 8, 6],
			"yr":	0.25,
			"index":	128
		}, {
			"position":	[3, 8, 6],
			"yr":	0,
			"index":	131
		}, {
			"position":	[2, 8, 7],
			"yr":	0.5,
			"index":	126
		}],
	"strats":	[{
			"params":	[0, 0, 0, 0, 0, 0, 0, 0],
			"position":	[32, 16, 17.5],
			"rotation":	[0, 0, 0],
			"name":	"Crystal",
			"waypoints":	[]
		}, {
			"params":	[0, 0, 0, 0, 0, 0, 0, 0],
			"position":	[32, 16, 32],
			"rotation":	[0, 0, 0],
			"name":	"Crystal",
			"waypoints":	[]
		}, {
			"params":	[0, 0, 0, 0, 0, 0, 0, 0],
			"position":	[16, 16, 32.5],
			"rotation":	[0, 0, 0],
			"name":	"Crystal",
			"waypoints":	[]
		}, {
			"params":	[0, 0, 0, 0, 0, 0, 0, 0],
			"position":	[48, 16, 32.5],
			"rotation":	[0, 0, 0],
			"name":	"Crystal",
			"waypoints":	[]
		}, {
			"params":	[0, 0, 0, 0, 0, 0, 0, 0],
			"position":	[32, 20, 96.5],
			"rotation":	[0, 0.49951171875, 0],
			"name":	"Gobbo",
			"waypoints":	[]
		}, {
			"params":	[458752, 65536, 1310720, 0, 0, 0, 0, 0],
			"position":	[32, 12, 69.39990234375],
			"rotation":	[0, 0, 0],
			"name":	"PlatformBridge",
			"waypoints":	[]
		}, {
			"params":	[0, 0, 0, 0, 0, 0, 0, 0],
			"position":	[32, 16, 6.5],
			"rotation":	[0, 0, 0],
			"name":	"NormalDoor",
			"waypoints":	[]
		}],
	"doors":	[{
			"position":	[2, 1, 0],
			"level":	10,
			"sublevel":	2,
			"flags":	["normal"],
			"id":	0
		}, {
			"position":	[2, 1, 1],
			"level":	0,
			"sublevel":	0,
			"flags":	["start"],
			"id":	0
		}],
	"point_lights":	[],
	"direct_lights":	[{
			"position":	[0, 1, 0],
			"colour":	[64, 64, 64]
		}, {
			"position":	[0, 0.5, 0.865966796875],
			"colour":	[255, 255, 128]
		}, {
			"position":	[0, 0.5, -0.000244140625],
			"colour":	[43, 43, 43]
		}],
	"ambient_colour":	[64, 64, 64]
}